odoo/addons/edi_sale_stock_oca/README.rst
odoo/addons/edi_sale_stock_oca/__init__.py
odoo/addons/edi_sale_stock_oca/__manifest__.py
odoo/addons/edi_sale_stock_oca/i18n/edi_sale_stock_oca.pot
odoo/addons/edi_sale_stock_oca/i18n/it.po
odoo/addons/edi_sale_stock_oca/models/__init__.py
odoo/addons/edi_sale_stock_oca/models/sale_order.py
odoo/addons/edi_sale_stock_oca/readme/CONTRIBUTORS.md
odoo/addons/edi_sale_stock_oca/readme/DESCRIPTION.md
odoo/addons/edi_sale_stock_oca/static/description/icon.png
odoo/addons/edi_sale_stock_oca/static/description/index.html
odoo/addons/edi_sale_stock_oca/tests/__init__.py
odoo/addons/edi_sale_stock_oca/tests/test_sale_action.py
odoo_addon_edi_sale_stock_oca-18.0.1.0.0.4.dist-info/METADATA
odoo_addon_edi_sale_stock_oca-18.0.1.0.0.4.dist-info/WHEEL
odoo_addon_edi_sale_stock_oca-18.0.1.0.0.4.dist-info/top_level.txt
odoo_addon_edi_sale_stock_oca-18.0.1.0.0.4.dist-info/RECORD
